gpplot/__init__.py
gpplot/plots.py
gpplot/style.py
gpplot-0.5.0.dist-info/AUTHORS.rst
gpplot-0.5.0.dist-info/LICENSE
gpplot-0.5.0.dist-info/METADATA
gpplot-0.5.0.dist-info/WHEEL
gpplot-0.5.0.dist-info/top_level.txt
gpplot-0.5.0.dist-info/RECORD
