Metadata-Version: 2.1
Name: gpplot
Version: 0.5.0
Summary: Plotting functions for the Genetic Perturbation Platform's R&D group at the Broad institute.
Home-page: https://github.com/gpp-rnd/gpplot
Author: Peter C DeWeirdt
Author-email: petedeweirdt@gmail.com
License: MIT license
Keywords: gpplot
Platform: UNKNOWN
Classifier: Development Status :: 2 - Pre-Alpha
Classifier: Intended Audience :: Developers
Classifier: License :: OSI Approved :: MIT License
Classifier: Natural Language :: English
Classifier: Programming Language :: Python :: 3
Classifier: Programming Language :: Python :: 3.6
Classifier: Programming Language :: Python :: 3.7
Classifier: Programming Language :: Python :: 3.8
Requires-Python: >=3.6
Requires-Dist: seaborn (>=0.10)
Requires-Dist: scipy (>=1.5)
Requires-Dist: numpy (>=1.19)
Requires-Dist: matplotlib (>=3.2)
Requires-Dist: pandas (>=1.0)
Requires-Dist: adjustText (>=0.7)
